celery_haystack/__init__.py
celery_haystack/conf.py
celery_haystack/indexes.py
celery_haystack/signals.py
celery_haystack/tasks.py
celery_haystack/test_settings.py
celery_haystack/utils.py
celery_haystack/tests/__init__.py
celery_haystack/tests/models.py
celery_haystack/tests/search_indexes.py
celery_haystack/tests/search_sites.py
celery_haystack/tests/tests.py
celery_haystack_ng-2.0.1.dist-info/AUTHORS
celery_haystack_ng-2.0.1.dist-info/LICENSE
celery_haystack_ng-2.0.1.dist-info/METADATA
celery_haystack_ng-2.0.1.dist-info/WHEEL
celery_haystack_ng-2.0.1.dist-info/top_level.txt
celery_haystack_ng-2.0.1.dist-info/RECORD
