Metadata-Version: 2.1
Name: celery-haystack-ng
Version: 2.0.1
Summary: An app for integrating Celery with Haystack
Home-page: http://celery-haystack-ng.rtfd.org/
Author: Dominik George
Author-email: dominik.george@teckids.org
Project-URL: Code, https://edugit.org/AlekSIS/libs/celery-haystack-ng
Classifier: Development Status :: 4 - Beta
Classifier: Environment :: Web Environment
Classifier: Framework :: Django
Classifier: Intended Audience :: Developers
Classifier: License :: OSI Approved :: BSD License
Classifier: Operating System :: OS Independent
Classifier: Programming Language :: Python :: 3
Classifier: Topic :: Utilities
License-File: LICENSE
License-File: AUTHORS
Requires-Dist: django-appconf >=0.4.1
Requires-Dist: django-haystack >=2.0
Requires-Dist: celery >=4.0
